{
  "configVersion": 1,
  "timestamp": 1716539569225,
  "index": "/mydemo/index.html",
  "assetGroups": [
    {
      "name": "app",
      "installMode": "prefetch",
      "updateMode": "prefetch",
      "cacheQueryOptions": {
        "ignoreVary": true
      },
      "urls": [
        "/mydemo/chunk-2QJ6S2UV.js",
        "/mydemo/chunk-2VOYZAVQ.js",
        "/mydemo/chunk-2XOPSDWW.js",
        "/mydemo/chunk-2YDAQ5XO.js",
        "/mydemo/chunk-32B5VTOS.js",
        "/mydemo/chunk-3QVHEZQR.js",
        "/mydemo/chunk-424VDZPE.js",
        "/mydemo/chunk-426OJ4HC.js",
        "/mydemo/chunk-43RORHHV.js",
        "/mydemo/chunk-4APAODWX.js",
        "/mydemo/chunk-4E2RX2Y5.js",
        "/mydemo/chunk-4Y4LWWLP.js",
        "/mydemo/chunk-55VXY33V.js",
        "/mydemo/chunk-572WCYSW.js",
        "/mydemo/chunk-5BDTYOXG.js",
        "/mydemo/chunk-5BGW4QSB.js",
        "/mydemo/chunk-5JYMR2VZ.js",
        "/mydemo/chunk-5QJFEBQY.js",
        "/mydemo/chunk-5X4HMWFG.js",
        "/mydemo/chunk-6IXVGNQ6.js",
        "/mydemo/chunk-6PB4UTOC.js",
        "/mydemo/chunk-7D6K5XYM.js",
        "/mydemo/chunk-7JRDXP6Y.js",
        "/mydemo/chunk-7ULJTZEA.js",
        "/mydemo/chunk-AEV27BIE.js",
        "/mydemo/chunk-AGYSVWMR.js",
        "/mydemo/chunk-AJPISUXH.js",
        "/mydemo/chunk-AMEKXVHQ.js",
        "/mydemo/chunk-B43CU5JX.js",
        "/mydemo/chunk-C6TWYN5N.js",
        "/mydemo/chunk-CHK2WM6F.js",
        "/mydemo/chunk-D2BHWG6E.js",
        "/mydemo/chunk-D5EFXCBS.js",
        "/mydemo/chunk-DIJMEIBG.js",
        "/mydemo/chunk-DL5JP6Y5.js",
        "/mydemo/chunk-EIKXRIPO.js",
        "/mydemo/chunk-ELRP26ST.js",
        "/mydemo/chunk-F4JBYUDS.js",
        "/mydemo/chunk-F7HVFZXP.js",
        "/mydemo/chunk-F7XBNY6P.js",
        "/mydemo/chunk-FFHGS4OM.js",
        "/mydemo/chunk-FHWRLDOV.js",
        "/mydemo/chunk-FQDN4LL4.js",
        "/mydemo/chunk-FVWOLPPA.js",
        "/mydemo/chunk-FYUKFWQR.js",
        "/mydemo/chunk-G24MWJQN.js",
        "/mydemo/chunk-G4FREUH4.js",
        "/mydemo/chunk-GJZKZXL4.js",
        "/mydemo/chunk-GOWQWRZR.js",
        "/mydemo/chunk-H2PHEXKY.js",
        "/mydemo/chunk-H3GX5QFY.js",
        "/mydemo/chunk-HC6MZPB3.js",
        "/mydemo/chunk-HCY5RKKD.js",
        "/mydemo/chunk-HK3XVI3N.js",
        "/mydemo/chunk-HLOI5HQ4.js",
        "/mydemo/chunk-HO5YGAP5.js",
        "/mydemo/chunk-HOUD6JRY.js",
        "/mydemo/chunk-I3CYGHQW.js",
        "/mydemo/chunk-I67V2A74.js",
        "/mydemo/chunk-ICC5SWU3.js",
        "/mydemo/chunk-IF62F7HH.js",
        "/mydemo/chunk-IFNCDCK6.js",
        "/mydemo/chunk-IGO6KG2K.js",
        "/mydemo/chunk-IMPYBVGF.js",
        "/mydemo/chunk-JBSQMKST.js",
        "/mydemo/chunk-JTNJ4DDT.js",
        "/mydemo/chunk-KVMLNMPK.js",
        "/mydemo/chunk-LF5XB4YN.js",
        "/mydemo/chunk-LNVDFSGK.js",
        "/mydemo/chunk-LOHYXAXQ.js",
        "/mydemo/chunk-LR4GPGNO.js",
        "/mydemo/chunk-MAW444UC.js",
        "/mydemo/chunk-MB3GCSZF.js",
        "/mydemo/chunk-MCRJI3T3.js",
        "/mydemo/chunk-MM5QLNJM.js",
        "/mydemo/chunk-NMYJD6OP.js",
        "/mydemo/chunk-NVMJBBE6.js",
        "/mydemo/chunk-O6OXH55J.js",
        "/mydemo/chunk-OBXDPQ3V.js",
        "/mydemo/chunk-OJMRJMRQ.js",
        "/mydemo/chunk-OMB27VJZ.js",
        "/mydemo/chunk-OPL2K2AH.js",
        "/mydemo/chunk-OQ736N2X.js",
        "/mydemo/chunk-PV6F2SN3.js",
        "/mydemo/chunk-QHCL4FB4.js",
        "/mydemo/chunk-QVZAFCSG.js",
        "/mydemo/chunk-QXUIN2RW.js",
        "/mydemo/chunk-REGAMSFI.js",
        "/mydemo/chunk-RJSB42HO.js",
        "/mydemo/chunk-RM7WKYGU.js",
        "/mydemo/chunk-S6GY76YP.js",
        "/mydemo/chunk-SWRAC6VR.js",
        "/mydemo/chunk-TBAMTHI7.js",
        "/mydemo/chunk-TH37HSPQ.js",
        "/mydemo/chunk-TQEIIVVC.js",
        "/mydemo/chunk-U6XZ4RNZ.js",
        "/mydemo/chunk-UBOG7ZAA.js",
        "/mydemo/chunk-UJQTAKBF.js",
        "/mydemo/chunk-UKMIYHEY.js",
        "/mydemo/chunk-UKPM56NG.js",
        "/mydemo/chunk-UZ4SJIDI.js",
        "/mydemo/chunk-V3ZGAREK.js",
        "/mydemo/chunk-VDBU3GXF.js",
        "/mydemo/chunk-WHNUF6NW.js",
        "/mydemo/chunk-WMEG6PAA.js",
        "/mydemo/chunk-WR5KXOBV.js",
        "/mydemo/chunk-X2GFXOIJ.js",
        "/mydemo/chunk-X337KSAB.js",
        "/mydemo/chunk-X76L2Z4W.js",
        "/mydemo/chunk-XFA4RM2S.js",
        "/mydemo/chunk-XINVV43G.js",
        "/mydemo/chunk-XKFVXN27.js",
        "/mydemo/chunk-XL67SWXR.js",
        "/mydemo/chunk-XOBEQGVG.js",
        "/mydemo/chunk-XOWHWB6O.js",
        "/mydemo/chunk-YET6W2RT.js",
        "/mydemo/chunk-YHLGTH4E.js",
        "/mydemo/chunk-YXXN5BVI.js",
        "/mydemo/chunk-Z5HBCMI3.js",
        "/mydemo/chunk-ZERLTBVK.js",
        "/mydemo/chunk-ZJDZMGSF.js",
        "/mydemo/chunk-ZYZJYRH3.js",
        "/mydemo/favicon.ico",
        "/mydemo/index.html",
        "/mydemo/main-LY7L2CFB.js",
        "/mydemo/manifest.webmanifest",
        "/mydemo/polyfills-RT5I6R6G.js",
        "/mydemo/styles-OJQM2ZXE.css"
      ],
      "patterns": []
    },
    {
      "name": "assets",
      "installMode": "lazy",
      "updateMode": "prefetch",
      "cacheQueryOptions": {
        "ignoreVary": true
      },
      "urls": [
        "/mydemo/assets/Fichier 1.svg",
        "/mydemo/assets/cross.svg",
        "/mydemo/assets/data.json",
        "/mydemo/assets/icons/icon-128x128.png",
        "/mydemo/assets/icons/icon-144x144.png",
        "/mydemo/assets/icons/icon-152x152.png",
        "/mydemo/assets/icons/icon-192x192.png",
        "/mydemo/assets/icons/icon-384x384.png",
        "/mydemo/assets/icons/icon-512x512.png",
        "/mydemo/assets/icons/icon-72x72.png",
        "/mydemo/assets/icons/icon-96x96.png",
        "/mydemo/assets/screenshots/mobile-1.jpg",
        "/mydemo/assets/screenshots/mobile-2.jpg",
        "/mydemo/assets/screenshots/mobile-3.jpg",
        "/mydemo/assets/screenshots/tablet-1.jpg",
        "/mydemo/assets/screenshots/tablet-2.jpg",
        "/mydemo/assets/valid.svg"
      ],
      "patterns": []
    }
  ],
  "dataGroups": [
    {
      "name": "api-resto",
      "patterns": [
        "\\/assets\\/data\\.json"
      ],
      "strategy": "performance",
      "maxSize": 100,
      "maxAge": 259200000,
      "timeoutMs": 10000,
      "cacheQueryOptions": {
        "ignoreVary": true
      },
      "version": 1
    }
  ],
  "hashTable": {
    "/mydemo/assets/Fichier 1.svg": "14ddc333e07c167cd8205f0deb75a01604488e23",
    "/mydemo/assets/cross.svg": "554fe3044887ce55a11014e0ddc2367588200016",
    "/mydemo/assets/data.json": "5357f5d146f91586ee3f9d3cd28a165167a7f2f5",
    "/mydemo/assets/icons/icon-128x128.png": "f912963bdc6d5a38d8f1dd0afbaab2ce8d657acb",
    "/mydemo/assets/icons/icon-144x144.png": "b155fd5f2fd5d2ea7760721063003c4cd95fd783",
    "/mydemo/assets/icons/icon-152x152.png": "eae6e0f0c8afb8aaae339e2a569b43e9238e5e6c",
    "/mydemo/assets/icons/icon-192x192.png": "15c4180454633880d98674aa7394656196c91584",
    "/mydemo/assets/icons/icon-384x384.png": "94a915751ef6c9282df9aea405ad679230631814",
    "/mydemo/assets/icons/icon-512x512.png": "1de182f76f7329dfa8f9fcdd1fdcdd695bea6a99",
    "/mydemo/assets/icons/icon-72x72.png": "aa88a6096bd973be7f6d7a5489bfa6bc2463f8c4",
    "/mydemo/assets/icons/icon-96x96.png": "7fb8f59c30ce2ff12c700321a0b39e14b3dc8f95",
    "/mydemo/assets/screenshots/mobile-1.jpg": "1a0816b5adc5476af46f4b32670c91f7edb81a4d",
    "/mydemo/assets/screenshots/mobile-2.jpg": "9b11310ddc70b3f27e905a44e9a2c14ffa0ab309",
    "/mydemo/assets/screenshots/mobile-3.jpg": "e2d7552448845331c6159964cb3e5f3fa83325fc",
    "/mydemo/assets/screenshots/tablet-1.jpg": "f00392837d80efee18fc375b09a8d5a86d450b68",
    "/mydemo/assets/screenshots/tablet-2.jpg": "9c7029604cbb8e42eeccc782ca967a602526da68",
    "/mydemo/assets/valid.svg": "37a3071aeaee20f8f80a300ab0cab3a12525ff29",
    "/mydemo/chunk-2QJ6S2UV.js": "fc336a84eb6681d8836b14943a1be5fbcf43aa0e",
    "/mydemo/chunk-2VOYZAVQ.js": "c2a53ceee6f6cbd07f11badb20efcaca88099b5f",
    "/mydemo/chunk-2XOPSDWW.js": "f358fe2fd776e3ff952d6ca3080ed4c03559ed68",
    "/mydemo/chunk-2YDAQ5XO.js": "37dbf338d92f5881d22439317d5bbbc588974ed4",
    "/mydemo/chunk-32B5VTOS.js": "d8cb31ee5d6d93870559255b39e5ce6012074fb0",
    "/mydemo/chunk-3QVHEZQR.js": "7e7ed9ca6f63eead354757ccdaa720a76d7ad79d",
    "/mydemo/chunk-424VDZPE.js": "2c2819b8f3bcd90867c41740edcac9d035c4affb",
    "/mydemo/chunk-426OJ4HC.js": "bbb60fea97f00452ea8ecebf5dfd6e0c9fa9491c",
    "/mydemo/chunk-43RORHHV.js": "ed1da150f59240901708d3939c19573d9c8a78e9",
    "/mydemo/chunk-4APAODWX.js": "0f5fcd2d1442a168d7521011e642272eb24e4aa3",
    "/mydemo/chunk-4E2RX2Y5.js": "7753abd484a3a3831ef7f30698680fc813818f06",
    "/mydemo/chunk-4Y4LWWLP.js": "9a5959dc583a1a8e6ec8b21420e64579495201b6",
    "/mydemo/chunk-55VXY33V.js": "23ebc91ec64b811f50a69c90c2c34154cebb5800",
    "/mydemo/chunk-572WCYSW.js": "46cbd506146e601bd085f40c805cff8d71431af1",
    "/mydemo/chunk-5BDTYOXG.js": "71f258fb556524968fbe3bb9af09d9177291872d",
    "/mydemo/chunk-5BGW4QSB.js": "ee12ed519ac54320ee115e41b55f80232821faea",
    "/mydemo/chunk-5JYMR2VZ.js": "922e47f191d8597e78543ab8c1e440335a5d045d",
    "/mydemo/chunk-5QJFEBQY.js": "876a117b630083e2eb3318167b0e1bd8378b4f56",
    "/mydemo/chunk-5X4HMWFG.js": "637e8d413bb1c292a5bfe547d31561915dc83e4e",
    "/mydemo/chunk-6IXVGNQ6.js": "bb1a364cd0a2ca3ff752af3daae67a871e93bb4c",
    "/mydemo/chunk-6PB4UTOC.js": "324699c63604e99c9daaecbd915e3e0ff810c33a",
    "/mydemo/chunk-7D6K5XYM.js": "93f07744c0e521238a6a4b6527587c46e7a4ef65",
    "/mydemo/chunk-7JRDXP6Y.js": "3ea8833e383c37972103528d37e4fcd22ebeb87b",
    "/mydemo/chunk-7ULJTZEA.js": "6cfa8c93d672e4be8d2c3fde4ccf5a84a580c401",
    "/mydemo/chunk-AEV27BIE.js": "c2718e46b2dddc213393d2cba476eca1922dd4f0",
    "/mydemo/chunk-AGYSVWMR.js": "46117d763949710757ccfca1fbcb7f7f6ddb1dfd",
    "/mydemo/chunk-AJPISUXH.js": "c1b92bc23783130d5f72986153a0867f57e24c85",
    "/mydemo/chunk-AMEKXVHQ.js": "2c3fd47f0697e403a4f204916acffea7d6ddc7ed",
    "/mydemo/chunk-B43CU5JX.js": "73485691923b650ef3c649d634c71239c18c0416",
    "/mydemo/chunk-C6TWYN5N.js": "45a62d80ab6dfeea649af8231a29943d7fd6bbca",
    "/mydemo/chunk-CHK2WM6F.js": "306f6f92c32ac015c84abdbf403d45c6b8367788",
    "/mydemo/chunk-D2BHWG6E.js": "8d5f1277dc95e7fa6a3ccad5074962b7cf6c98ab",
    "/mydemo/chunk-D5EFXCBS.js": "52d17bc185c70fe2345888833fd37ae08e864ab8",
    "/mydemo/chunk-DIJMEIBG.js": "5c8e288881e54163bb09e397c602c993ea32818e",
    "/mydemo/chunk-DL5JP6Y5.js": "fcae8a1c12db5f7b3c7b524da80757ac9bb99ff3",
    "/mydemo/chunk-EIKXRIPO.js": "48f4c3bb0070002e109e6cdd3fa48817e991429b",
    "/mydemo/chunk-ELRP26ST.js": "a091f3700008628d222644b9709fa8522e6f3055",
    "/mydemo/chunk-F4JBYUDS.js": "82a6be60682f01bd8f49a84fe7cf1e62491fe22e",
    "/mydemo/chunk-F7HVFZXP.js": "35bd4a67709fcf57044336db5117a2c5dbdc2d15",
    "/mydemo/chunk-F7XBNY6P.js": "f8aa0d06431c3ca3e5a7aa7435cfbea110325570",
    "/mydemo/chunk-FFHGS4OM.js": "db3b51a5c1408f0f6478fc7daec4e181a439302c",
    "/mydemo/chunk-FHWRLDOV.js": "af34630f4a0155ff90bda01d5b52c31de59b1366",
    "/mydemo/chunk-FQDN4LL4.js": "2a22e576ddb1a4f8864f51f58a597ff1b8345141",
    "/mydemo/chunk-FVWOLPPA.js": "3e57ab8e699c4b64e1a54d8653b3a55964db234c",
    "/mydemo/chunk-FYUKFWQR.js": "4b9ab8aaf9bee57de53d7040382c6e7988fd1de5",
    "/mydemo/chunk-G24MWJQN.js": "42c13d06bf36aca686c70dae2396cab43d7a73e3",
    "/mydemo/chunk-G4FREUH4.js": "0e6623d76770c20e20be6d0f5555f4d1cc0d2997",
    "/mydemo/chunk-GJZKZXL4.js": "27ca889a1a8ce9c98bae8853afda2496b2df5084",
    "/mydemo/chunk-GOWQWRZR.js": "2e65111b67119b29f6c276cb858efa3cbd1d46c9",
    "/mydemo/chunk-H2PHEXKY.js": "5b6d47107e58373ea3dc79e4e6878406e21505e8",
    "/mydemo/chunk-H3GX5QFY.js": "a1a0e4af9e4fb2e3189311f19c417aa1e80f5260",
    "/mydemo/chunk-HC6MZPB3.js": "3d8b0e78a6fe064a4c882a0599f7bc6a91502b47",
    "/mydemo/chunk-HCY5RKKD.js": "ef795f7b8699beae018c6c1e658115f61e548c2e",
    "/mydemo/chunk-HK3XVI3N.js": "a1a4bb9e67b130d694d220e316c6b45552f2cf3d",
    "/mydemo/chunk-HLOI5HQ4.js": "9f08a923ff7ce5d28ab0787b6d3ba235850e4b75",
    "/mydemo/chunk-HO5YGAP5.js": "92ccd4678770f6453314a66f44031a6fae5a43ac",
    "/mydemo/chunk-HOUD6JRY.js": "985012469ed78c254f129543f7421864a52d4a29",
    "/mydemo/chunk-I3CYGHQW.js": "ce433548ad40f8289fa2ce40d6b6689878ebf02b",
    "/mydemo/chunk-I67V2A74.js": "4a7ac04022cc1a69fc4e63951403929b8763727b",
    "/mydemo/chunk-ICC5SWU3.js": "bfbe6731fafe0b1501be5ca1cc64bc4978feae8b",
    "/mydemo/chunk-IF62F7HH.js": "d8a9e274128316714b0792becb38cab8fb6963de",
    "/mydemo/chunk-IFNCDCK6.js": "a7ce01f4205ce5ffb288071f1ad4069acc76c8f2",
    "/mydemo/chunk-IGO6KG2K.js": "465d203205e2148686baf1c392299a3f4753dbf7",
    "/mydemo/chunk-IMPYBVGF.js": "5301926efcc1dbf959be93a622e203e6b9ebd3b1",
    "/mydemo/chunk-JBSQMKST.js": "f8c5955edee23378592573562fe43b9b5229ef97",
    "/mydemo/chunk-JTNJ4DDT.js": "05ee009d7d5d4c714a11811d79111f2eba5e76c1",
    "/mydemo/chunk-KVMLNMPK.js": "6b9d3a7b578bbb5f66c097999f5d74b27fc272b3",
    "/mydemo/chunk-LF5XB4YN.js": "9a4312a44cc8ab8573488a48a18c01a6bb352c6b",
    "/mydemo/chunk-LNVDFSGK.js": "90dc0d9b337f92375c21e23c8b0580a92d6d1972",
    "/mydemo/chunk-LOHYXAXQ.js": "82a58ce2bc7cd9bfca2e704b08c5453bac6b80f6",
    "/mydemo/chunk-LR4GPGNO.js": "46618b63d8ff3c3b7643212d3f96057daf5c6c3b",
    "/mydemo/chunk-MAW444UC.js": "dd6914a26b4913e6bfe645fc36251afb60573e3a",
    "/mydemo/chunk-MB3GCSZF.js": "5d4fb1d5542ba4c93d48dbffa711f1c8c0b7e658",
    "/mydemo/chunk-MCRJI3T3.js": "9a4312a44cc8ab8573488a48a18c01a6bb352c6b",
    "/mydemo/chunk-MM5QLNJM.js": "565ca77d12ec1cc1f7a733a9371b32d0d575d800",
    "/mydemo/chunk-NMYJD6OP.js": "0175118cb5ac5fb567dcfbf6a8bcb81ace8edf1a",
    "/mydemo/chunk-NVMJBBE6.js": "53ed76daa2b1a2ffc0a9317ad2deec9e6f34eff0",
    "/mydemo/chunk-O6OXH55J.js": "3f1fcbda3d2b1a84d665d368a082773f525ef93f",
    "/mydemo/chunk-OBXDPQ3V.js": "b9f98a370e268e3ec02471efe53af42a11782fb6",
    "/mydemo/chunk-OJMRJMRQ.js": "bde6b152870e6d215930b54760877a64c9aea6d1",
    "/mydemo/chunk-OMB27VJZ.js": "aab49b7d135e3c8985341714c4b6c51be00cbade",
    "/mydemo/chunk-OPL2K2AH.js": "45a770489a7c1bc1adddab1338af0cf609304797",
    "/mydemo/chunk-OQ736N2X.js": "586584b5476fcd916b9617cd0b0a40f35aefcf38",
    "/mydemo/chunk-PV6F2SN3.js": "40a740bfb1fcc19ddec4a8102774fb1b36f8ced9",
    "/mydemo/chunk-QHCL4FB4.js": "3c508a6a15ad6739139e759ebceb4a4d30282742",
    "/mydemo/chunk-QVZAFCSG.js": "d962419c73c9ea57589f512729b6d3ffb40abc07",
    "/mydemo/chunk-QXUIN2RW.js": "0e81fc98c677116e89bcfcb9963bdbb3b8f2e91b",
    "/mydemo/chunk-REGAMSFI.js": "f4ed665f1362132b66b9bb655dee12a5eee2168d",
    "/mydemo/chunk-RJSB42HO.js": "3e18171dab7f916f35711667282473c5c70f836f",
    "/mydemo/chunk-RM7WKYGU.js": "771642085d09bda4f250180dad43ebc913d632b3",
    "/mydemo/chunk-S6GY76YP.js": "d31851345562f9c2ffd1413c85b42355ac3dc60d",
    "/mydemo/chunk-SWRAC6VR.js": "de630878397bfe3ed0b9477b79112d9ce1817bdc",
    "/mydemo/chunk-TBAMTHI7.js": "2877f2602a57c248ff4381d520d764ec906d5325",
    "/mydemo/chunk-TH37HSPQ.js": "0829e9edb9cd2a400a7c4fdbf08473e5e8bb7ff3",
    "/mydemo/chunk-TQEIIVVC.js": "c7296efb75e44b6c5b31377a35aaf8879f17f8b1",
    "/mydemo/chunk-U6XZ4RNZ.js": "4c21cffab1518e2ef319281894ab2fd2927235da",
    "/mydemo/chunk-UBOG7ZAA.js": "cc9bb78851595ae2cd49116dfc2166a8ed9d0ebc",
    "/mydemo/chunk-UJQTAKBF.js": "0e0dfa26022aa8965ad4076857faee517f207538",
    "/mydemo/chunk-UKMIYHEY.js": "d844cfb70199a042e606c0acae6061b69408fe3e",
    "/mydemo/chunk-UKPM56NG.js": "b9dbb26fd179d45a3756ad2e74737ff889eb336a",
    "/mydemo/chunk-UZ4SJIDI.js": "d65bf06b2fcb4a6a1f2a3d0ab1aac5a5cdce95d1",
    "/mydemo/chunk-V3ZGAREK.js": "b755475df8ba6a97e5c5a12fbef7b1adae7fc0e7",
    "/mydemo/chunk-VDBU3GXF.js": "5522c5fb2023c8ac536812b551224bf824728a41",
    "/mydemo/chunk-WHNUF6NW.js": "ef6b64cd01e5081f504acf732393790ed35665f7",
    "/mydemo/chunk-WMEG6PAA.js": "62921a73225ecbaa97d351c06b87671b73abb380",
    "/mydemo/chunk-WR5KXOBV.js": "355846e13d0bf9c47834fd281c1f5b7ba8f36059",
    "/mydemo/chunk-X2GFXOIJ.js": "3c1f28a7fc48a4e006ae7f998f50b42f70fffd47",
    "/mydemo/chunk-X337KSAB.js": "1d3858167722530e21e2c537e484b894d53abde0",
    "/mydemo/chunk-X76L2Z4W.js": "8756a14a76bd17f23f97929c71c1533a18e12796",
    "/mydemo/chunk-XFA4RM2S.js": "7c8f3040a7e23b4557a0292560b1420619dd04d9",
    "/mydemo/chunk-XINVV43G.js": "a390dcaca31fc9d7b7338b8d74b18508fd0d877c",
    "/mydemo/chunk-XKFVXN27.js": "42c365278f351b2766b9d7511d6b200c66d7cc8b",
    "/mydemo/chunk-XL67SWXR.js": "f1f24c697592e1afdf40b93d56eac68366aac184",
    "/mydemo/chunk-XOBEQGVG.js": "17c4061059de34f44aa7cdc79ec5922703501589",
    "/mydemo/chunk-XOWHWB6O.js": "ab13865e8c911c7a6794de2de4476e7dfd1c2797",
    "/mydemo/chunk-YET6W2RT.js": "5a4f9b4ea097ee859211571183e38b1f97fe8caf",
    "/mydemo/chunk-YHLGTH4E.js": "cfedebcf61dee17858b8b29fddf49b39205b4719",
    "/mydemo/chunk-YXXN5BVI.js": "6bf158389b4910e70d98a91391830f282b08d1fc",
    "/mydemo/chunk-Z5HBCMI3.js": "966dffd6f8d158a9a2e1c52aa8769670b893f777",
    "/mydemo/chunk-ZERLTBVK.js": "cec9e683b44924325dcc33521213d33ded6c8cfa",
    "/mydemo/chunk-ZJDZMGSF.js": "2015fb13310a001045faaec6d8a9efe140418eb3",
    "/mydemo/chunk-ZYZJYRH3.js": "e54358870c2d5a145dc5a5fcbee492bbbeacfd3a",
    "/mydemo/favicon.ico": "9c39f434fe1261f68c5e3eefdf734630d99c5670",
    "/mydemo/index.html": "fd41037672a5a5145b697392973bcd9aadfa32d5",
    "/mydemo/main-LY7L2CFB.js": "5dfaf04d2fbb7fa7510d5e0f1972e47c55317d9a",
    "/mydemo/manifest.webmanifest": "eb2cef9838b73da8502f5eb6f2182e8673f8ad8f",
    "/mydemo/polyfills-RT5I6R6G.js": "fe9f024576f21ff6314cf8f8332cde58b9a12416",
    "/mydemo/styles-OJQM2ZXE.css": "7a58328c936116832be61b9ce786882527be51ba"
  },
  "navigationUrls": [
    {
      "positive": true,
      "regex": "^\\/.*$"
    },
    {
      "positive": false,
      "regex": "^\\/(?:.+\\/)?[^/]*\\.[^/]*$"
    },
    {
      "positive": false,
      "regex": "^\\/(?:.+\\/)?[^/]*__[^/]*$"
    },
    {
      "positive": false,
      "regex": "^\\/(?:.+\\/)?[^/]*__[^/]*\\/.*$"
    }
  ],
  "navigationRequestStrategy": "performance"
}